dcmpi/__init__.py
dcmpi/_version.py
dcmpi/custom_info.py
dcmpi/dcmpi_analyze_dir.py
dcmpi/dcmpi_explorer.py
dcmpi/dcmpi_explorer_cli.py
dcmpi/dcmpi_explorer_gui.py
dcmpi/dcmpi_gui_qt.py
dcmpi/dcmpi_monitor_folder.py
dcmpi/dcmpi_run.py
dcmpi/dcmpi_run_cli.py
dcmpi/dcmpi_run_gui.py
dcmpi/dcmpi_update.py
dcmpi/do_acquire_sources.py
dcmpi/do_backup.py
dcmpi/do_report.py
dcmpi/do_sorting.py
dcmpi/get_info.py
dcmpi/get_meta.py
dcmpi/get_nifti.py
dcmpi/get_prot.py
dcmpi/util.py
dcmpi/report_templates/acquisition_parameter_template.html
dcmpi/report_templates/acquisition_template.html
dcmpi/report_templates/report_template.html
dcmpi-0.0.2.8.data/data/share/icons/dcmpi_logo.svg
dcmpi-0.0.2.8.dist-info/DESCRIPTION.rst
dcmpi-0.0.2.8.dist-info/METADATA
dcmpi-0.0.2.8.dist-info/RECORD
dcmpi-0.0.2.8.dist-info/WHEEL
dcmpi-0.0.2.8.dist-info/entry_points.txt
dcmpi-0.0.2.8.dist-info/metadata.json
dcmpi-0.0.2.8.dist-info/top_level.txt
