Metadata-Version: 2.0
Name: dcmpi
Version: 0.0.2.8
Summary: DICOM Preprocessing Interface.
Home-page: https://github.com/norok2/dcmpi
Author: Riccardo Metere
Author-email: rick@metere.it
License: GPLv3+
Keywords: dicom dcm preprocessing
Platform: UNKNOWN
Classifier: Development Status :: 3 - Alpha
Classifier: Environment :: Console
Classifier: Environment :: Console :: Curses
Classifier: Environment :: Win32 (MS Windows)
Classifier: Environment :: X11 Applications
Classifier: Intended Audience :: Science/Research
Classifier: Intended Audience :: Healthcare Industry
Classifier: Intended Audience :: System Administrators
Classifier: Topic :: Scientific/Engineering
Classifier: Topic :: Scientific/Engineering :: Medical Science Apps.
Classifier: Topic :: System :: Archiving
Classifier: Topic :: System :: Systems Administration
Classifier: Topic :: System :: Monitoring
Classifier: Topic :: Utilities
Classifier: Operating System :: POSIX
Classifier: Natural Language :: English
Classifier: Operating System :: OS Independent
Classifier: License :: OSI Approved :: GNU General Public License v3 or later (GPLv3+)
Classifier: Programming Language :: Python
Classifier: Programming Language :: Python :: 2
Classifier: Programming Language :: Python :: 3
Provides-Extra: blessings
Requires-Dist: appdirs
Requires-Dist: blessed
Requires-Dist: dicom2nifti
Requires-Dist: flyingcircus
Requires-Dist: pydicom
Requires-Dist: pytk
Provides-Extra: blessings
Requires-Dist: blessings; extra == 'blessings'
